torchtracer/__init__.py
torchtracer/tracer.py
torchtracer/data/__init__.py
torchtracer/data/config.py
torchtracer/data/model.py
torchtracer/utils/__init__.py
torchtracer/utils/storeman.py
torchtracer-0.1.5.dist-info/METADATA
torchtracer-0.1.5.dist-info/RECORD
torchtracer-0.1.5.dist-info/WHEEL
torchtracer-0.1.5.dist-info/top_level.txt
