Metadata-Version: 2.1
Name: torchtracer
Version: 0.1.5
Summary: A python package for visualization and storage management in a pytorch AI task.
Home-page: https://github.com/OIdiotLin/torchtracer
Author: OIdiotLin
Author-email: oidiotlin@gmail.com
Maintainer: OIdiotLin
Maintainer-email: oidiotlin@gmail.com
License: MIT License
Platform: UNKNOWN
Classifier: Programming Language :: Python :: 3
Classifier: License :: OSI Approved :: MIT License
Classifier: Operating System :: OS Independent
Requires-Dist: matplotlib
Requires-Dist: numpy
